pyguardian/__init__.py
pyguardian/_guardian.py
pyguardian/errors/__init__.py
pyguardian/errors/grammar.py
pyguardian/tests/__init__.py
pyguardian/tests/ctx_managers.py
pyguardian/tests/test_class.py
pyguardian/tests/test_exceptions.py
pyguardian/tests/test_successful.py
pyguardian/tests/test_warnings.py
pyguardian-0.0.3.dist-info/LICENSE
pyguardian-0.0.3.dist-info/METADATA
pyguardian-0.0.3.dist-info/WHEEL
pyguardian-0.0.3.dist-info/top_level.txt
pyguardian-0.0.3.dist-info/RECORD
